{
  "swagger": "2.0",
  "info": {
    "version": "1.0.0",
    "title": "REST API",
    "description": ""
  },
  "host": "localhost:3000",
  "basePath": "/",
  "schemes": [
    "http"
  ],
  "paths": {
    "/": {
      "post": {
        "description": "",
        "parameters": [
          {
            "name": "body",
            "in": "body",
            "schema": {
              "type": "object",
              "properties": {
                "groupId": {
                  "example": "any"
                }
              }
            }
          }
        ],
        "responses": {
          "204": {
            "description": "No Content"
          }
        }
      }
    },
    "/{groupId}": {
      "get": {
        "description": "",
        "parameters": [
          {
            "name": "groupId",
            "in": "path",
            "required": true,
            "type": "string"
          },
          {
            "name": "offset",
            "in": "query",
            "type": "string"
          }
        ],
        "responses": {
          "200": {
            "description": "OK"
          }
        }
      }
    },
    "/{graphId}": {
      "post": {
        "description": "",
        "parameters": [
          {
            "name": "graphId",
            "in": "path",
            "required": true,
            "type": "string"
          }
        ],
        "responses": {
          "204": {
            "description": "No Content"
          }
        }
      },
      "get": {
        "description": "",
        "parameters": [
          {
            "name": "graphId",
            "in": "path",
            "required": true,
            "type": "string"
          }
        ],
        "responses": {
          "200": {
            "description": "OK"
          }
        }
      }
    },
    "/{limit}": {
      "get": {
        "description": "",
        "parameters": [
          {
            "name": "limit",
            "in": "path",
            "required": true,
            "type": "string"
          }
        ],
        "responses": {
          "200": {
            "description": "OK"
          }
        }
      }
    },
    "/users/{groupId}": {
      "get": {
        "description": "",
        "parameters": [
          {
            "name": "groupId",
            "in": "path",
            "required": true,
            "type": "string"
          }
        ],
        "responses": {
          "200": {
            "description": "OK"
          }
        }
      }
    },
    "/search/{groupId}/": {
      "get": {
        "description": "",
        "parameters": [
          {
            "name": "groupId",
            "in": "path",
            "required": true,
            "type": "string"
          }
        ],
        "responses": {
          "200": {
            "description": "OK"
          }
        }
      }
    },
    "/group/{groupId}": {
      "post": {
        "description": "",
        "parameters": [
          {
            "name": "groupId",
            "in": "path",
            "required": true,
            "type": "string"
          },
          {
            "name": "body",
            "in": "body",
            "schema": {
              "type": "object",
              "properties": {
                "date": {
                  "example": "any"
                },
                "userEmail": {
                  "example": "any"
                }
              }
            }
          }
        ],
        "responses": {
          "200": {
            "description": "OK"
          }
        }
      },
      "get": {
        "description": "",
        "parameters": [
          {
            "name": "groupId",
            "in": "path",
            "required": true,
            "type": "string"
          },
          {
            "name": "start",
            "in": "query",
            "type": "string"
          },
          {
            "name": "end",
            "in": "query",
            "type": "string"
          }
        ],
        "responses": {
          "200": {
            "description": "OK"
          }
        }
      }
    },
    "/{noteId}": {
      "get": {
        "description": "",
        "parameters": [
          {
            "name": "noteId",
            "in": "path",
            "required": true,
            "type": "string"
          }
        ],
        "responses": {
          "200": {
            "description": "OK"
          }
        }
      },
      "patch": {
        "description": "",
        "parameters": [
          {
            "name": "noteId",
            "in": "path",
            "required": true,
            "type": "string"
          },
          {
            "name": "body",
            "in": "body",
            "schema": {
              "type": "object",
              "properties": {
                "title": {
                  "example": "any"
                },
                "content": {
                  "example": "any"
                }
              }
            }
          }
        ],
        "responses": {
          "200": {
            "description": "OK"
          }
        }
      },
      "delete": {
        "description": "",
        "parameters": [
          {
            "name": "noteId",
            "in": "path",
            "required": true,
            "type": "string"
          }
        ],
        "responses": {
          "204": {
            "description": "No Content"
          }
        }
      }
    },
    "/group/{groupId}/task/{taskId}": {
      "get": {
        "description": "",
        "parameters": [
          {
            "name": "groupId",
            "in": "path",
            "required": true,
            "type": "string"
          },
          {
            "name": "taskId",
            "in": "path",
            "required": true,
            "type": "string"
          }
        ],
        "responses": {
          "200": {
            "description": "OK"
          }
        }
      }
    },
    "/{taskId}/repeats": {
      "get": {
        "description": "",
        "parameters": [
          {
            "name": "taskId",
            "in": "path",
            "required": true,
            "type": "string"
          }
        ],
        "responses": {
          "200": {
            "description": "OK"
          }
        }
      }
    },
    "/group/{groupId}/range": {
      "get": {
        "description": "",
        "parameters": [
          {
            "name": "groupId",
            "in": "path",
            "required": true,
            "type": "string"
          },
          {
            "name": "start",
            "in": "query",
            "type": "string"
          },
          {
            "name": "end",
            "in": "query",
            "type": "string"
          }
        ],
        "responses": {
          "200": {
            "description": "OK"
          }
        }
      }
    },
    "/{taskId}": {
      "put": {
        "description": "",
        "parameters": [
          {
            "name": "taskId",
            "in": "path",
            "required": true,
            "type": "string"
          },
          {
            "name": "body",
            "in": "body",
            "schema": {
              "type": "object",
              "properties": {
                "repeat_pattern": {
                  "example": "any"
                }
              }
            }
          }
        ],
        "responses": {
          "200": {
            "description": "OK"
          }
        }
      },
      "delete": {
        "description": "",
        "parameters": [
          {
            "name": "taskId",
            "in": "path",
            "required": true,
            "type": "string"
          },
          {
            "name": "end_date",
            "in": "query",
            "type": "string"
          }
        ],
        "responses": {
          "204": {
            "description": "No Content"
          }
        }
      }
    },
    "/{userId}": {
      "get": {
        "description": "",
        "parameters": [
          {
            "name": "userId",
            "in": "path",
            "required": true,
            "type": "string"
          }
        ],
        "responses": {
          "200": {
            "description": "OK"
          }
        }
      },
      "patch": {
        "description": "",
        "parameters": [
          {
            "name": "userId",
            "in": "path",
            "required": true,
            "type": "string"
          }
        ],
        "responses": {
          "204": {
            "description": "No Content"
          }
        }
      }
    },
    "/{userId}/group": {
      "post": {
        "description": "",
        "parameters": [
          {
            "name": "userId",
            "in": "path",
            "required": true,
            "type": "string"
          },
          {
            "name": "body",
            "in": "body",
            "schema": {
              "type": "object",
              "properties": {
                "groupId": {
                  "example": "any"
                }
              }
            }
          }
        ],
        "responses": {
          "204": {
            "description": "No Content"
          }
        }
      }
    },
    "/groupId/{userId}": {
      "get": {
        "description": "",
        "parameters": [
          {
            "name": "userId",
            "in": "path",
            "required": true,
            "type": "string"
          }
        ],
        "responses": {
          "200": {
            "description": "OK"
          }
        }
      }
    },
    "/{userId}/{groupId}": {
      "delete": {
        "description": "",
        "parameters": [
          {
            "name": "userId",
            "in": "path",
            "required": true,
            "type": "string"
          },
          {
            "name": "groupId",
            "in": "path",
            "required": true,
            "type": "string"
          }
        ],
        "responses": {
          "204": {
            "description": "No Content"
          }
        }
      }
    },
    "/{graphId}/{timestamp}": {
      "delete": {
        "description": "",
        "parameters": [
          {
            "name": "graphId",
            "in": "path",
            "required": true,
            "type": "string"
          },
          {
            "name": "timestamp",
            "in": "path",
            "required": true,
            "type": "string"
          }
        ],
        "responses": {
          "204": {
            "description": "No Content"
          }
        }
      },
      "patch": {
        "description": "",
        "parameters": [
          {
            "name": "graphId",
            "in": "path",
            "required": true,
            "type": "string"
          },
          {
            "name": "timestamp",
            "in": "path",
            "required": true,
            "type": "string"
          },
          {
            "name": "body",
            "in": "body",
            "schema": {
              "type": "object",
              "properties": {
                "measurement": {
                  "example": "any"
                }
              }
            }
          }
        ],
        "responses": {
          "200": {
            "description": "OK"
          }
        }
      }
    }
  }
}